{
 "name": "GeneX_1534",
 "description": "GeneX Project is a unique and rare 3D omnichain NFT collection of 5555 NFTs generated by random generation of over 200 features. The collection offers the opportunity to easily switch between networks hosting LayerZero technology. \n\n [Get live updates on our Twitter](https://twitter.com/genexprojectnft) \n\n [Join the community in our Discord](http://discord.gg/9jh7A3J9fV)",
 "NFT_DNA": "16-13-20-4-1-17-1-35-1-3",
 "NFT_Variants": {
  "Back": "None_16_70",
  "Background": "Orange_13_0",
  "Clothes": "Sweater SNK_20_5",
  "Earring": "Single Coin_4_7",
  "Eyebrow": "Normal_1_0",
  "Eyecolor": "Gold_17_3",
  "Eyewear": "Round Glass_1_5",
  "Hair": "TRIHA BLU_35_0",
  "Mouth": "Lock_1_7",
  "Skin": "Magma_3_5"
 }
}
