{
 "name": "GeneX_1156",
 "description": "GeneX Project is a unique and rare 3D omnichain NFT collection of 5555 NFTs generated by random generation of over 200 features. The collection offers the opportunity to easily switch between networks hosting LayerZero technology. \n\n [Get live updates on our Twitter](https://twitter.com/genexprojectnft) \n\n [Join the community in our Discord](http://discord.gg/9jh7A3J9fV)",
 "NFT_DNA": "16-6-21-14-3-7-21-24-19-10",
 "NFT_Variants": {
  "Back": "None_16_70",
  "Background": "Purple_6_0",
  "Clothes": "Sweater GRN_21_5",
  "Earring": "None_14_35",
  "Eyebrow": "Serious_3_0",
  "Eyecolor": "Zombie_7_5",
  "Eyewear": "Tihulu Blue_21_5",
  "Hair": "KEKO BRW_24_0",
  "Mouth": "BTC Mask_19_6",
  "Skin": "Goldhex_10_5"
 }
}
