{
 "name": "GeneX_947",
 "description": "GeneX Project is a unique and rare 3D omnichain NFT collection of 5555 NFTs generated by random generation of over 200 features. The collection offers the opportunity to easily switch between networks hosting LayerZero technology. \n\n [Get live updates on our Twitter](https://twitter.com/genexprojectnft) \n\n [Join the community in our Discord](http://discord.gg/9jh7A3J9fV)",
 "NFT_DNA": "16-9-20-1-3-24-19-3-6-5",
 "NFT_Variants": {
  "Back": "None_16_70",
  "Background": "Gray_9_0",
  "Clothes": "Sweater SNK_20_5",
  "Earring": "Snowflake_1_4",
  "Eyebrow": "Serious_3_0",
  "Eyecolor": "Dollar_24_5",
  "Eyewear": "Goggles Brown_19_3",
  "Hair": "TORIGHT BLK_3_0",
  "Mouth": "Purple Ivory_6_6",
  "Skin": "Antratorium_5_6"
 }
}
