{
 "name": "GeneX_2731",
 "description": "GeneX Project is a unique and rare 3D omnichain NFT collection of 5555 NFTs generated by random generation of over 200 features. The collection offers the opportunity to easily switch between networks hosting LayerZero technology. \n\n [Get live updates on our Twitter](https://twitter.com/genexprojectnft) \n\n [Join the community in our Discord](http://discord.gg/9jh7A3J9fV)",
 "NFT_DNA": "16-5-30-3-2-8-6-7-16-2",
 "NFT_Variants": {
  "Back": "None_16_70",
  "Background": "Pink_5_0",
  "Clothes": "Clothe R_30_4",
  "Earring": "Point_3_7",
  "Eyebrow": "Innocent_2_0",
  "Eyecolor": "Cateye_8_4",
  "Eyewear": "Retro Blue_6_5",
  "Hair": "HAWAT GRN_7_0",
  "Mouth": "Crown_16_5",
  "Skin": "Cyber_2_7"
 }
}
