{
 "name": "GeneX_483",
 "description": "GeneX Project is a unique and rare 3D omnichain NFT collection of 5555 NFTs generated by random generation of over 200 features. The collection offers the opportunity to easily switch between networks hosting LayerZero technology. \n\n [Get live updates on our Twitter](https://twitter.com/genexprojectnft) \n\n [Join the community in our Discord](http://discord.gg/9jh7A3J9fV)",
 "NFT_DNA": "7-4-34-14-3-4-12-21-9-2",
 "NFT_Variants": {
  "Back": "Golden Sharp_7_0.50",
  "Background": "Blue_4_0",
  "Clothes": "Glass GRY_34_2",
  "Earring": "None_14_35",
  "Eyebrow": "Serious_3_0",
  "Eyecolor": "ST-BLUE_4_5",
  "Eyewear": "MetaGlasses Blue_12_3",
  "Hair": "MOHIKAN DRK_21_0",
  "Mouth": "Rasphre_9_6",
  "Skin": "Cyber_2_7"
 }
}
